setup.py
synonymscrawler/__init__.py
synonymscrawler/blockspring_synonyms_crawler.py
synonymscrawler/simple_synonyms_crawler.py
synonymscrawler/synonyms_crawler.py
synonymscrawler.egg-info/PKG-INFO
synonymscrawler.egg-info/SOURCES.txt
synonymscrawler.egg-info/dependency_links.txt
synonymscrawler.egg-info/requires.txt
synonymscrawler.egg-info/top_level.txt