Metadata-Version: 1.1
Name: synonymscrawler
Version: 1.0.0
Summary: Python Synonyms Crawler Implementation
Home-page: https://github.com/SaiWebApps/PySynonymsCrawler
Author: Sairam Krishnan
Author-email: sairambkrishnan@gmail.com
License: MIT
Download-URL: https://github.com/SaiWebApps/PySynonymsCrawler/tarball/1.0.0
Keywords: Python,synonyms-crawler,web-scraping,text-parsing
Platform: UNKNOWN
